pbi_git/__init__.py
pbi_git/change_classes.py
pbi_git/main.py
pbi_git/ssas.py
pbi_git/to_markdown.py
pbi_git/utils.py
pbi_git/layout_diffs/__init__.py
pbi_git/layout_diffs/filters.py
pbi_git/layout_diffs/gen_svgs.py
pbi_git/layout_diffs/layout.py
pbi_git/layout_diffs/section.py
pbi_git/layout_diffs/visual.py
pbi_git/svgs/_added.svg
pbi_git/svgs/_deleted.svg
pbi_git/svgs/_moved.svg
pbi_git/svgs/bar.svg
pbi_git/svgs/card.svg
pbi_git/svgs/donut.svg
pbi_git/svgs/horizontal_bar.svg
pbi_git/svgs/horizontal_stacked_bar.svg
pbi_git/svgs/map.svg
pbi_git/svgs/pie.svg
pbi_git/svgs/scatter.svg
pbi_git/svgs/stacked_bar.svg
pbi_git/svgs/text_box.svg
pbi_git/templates/github-dark.css
pbi_git/templates/single/layout.md
pbi_git/templates/single/main.md
pbi_git/templates/single/ssas.md
pbi_git/templates/single/summary.md
pbi_git/templates/split/layout.md
pbi_git/templates/split/section.md
pbi_git/templates/split/ssas.md
pbi_git/templates/split/summary.md
pbi_git/templates/split/visual.md
pbi_git-0.5.1.dist-info/METADATA
pbi_git-0.5.1.dist-info/WHEEL
pbi_git-0.5.1.dist-info/licenses/LICENSE
pbi_git-0.5.1.dist-info/RECORD
