Metadata-Version: 2.4
Name: pbi-git
Version: 0.5.1
Summary: Creation of git diff reports for Power BI files
Project-URL: Homepage, https://github.com/douglassimonsen/pbi_git
Project-URL: Documentation, https://douglassimonsen.github.io/pbi_git/
License-File: LICENSE
Requires-Python: >=3.11.0
Requires-Dist: pbi-core>=0.3.7
Requires-Dist: svgwrite>=1.4.3
Provides-Extra: dev
Requires-Dist: ruff; extra == 'dev'
Provides-Extra: docs
Requires-Dist: mkdocs-material>=9.6.16; extra == 'docs'
Requires-Dist: mkdocs>=1.6.1; extra == 'docs'
Requires-Dist: mkdocstrings-python>=0.30.0; extra == 'docs'
Provides-Extra: pdf
Requires-Dist: linkify-it-py>=2.0.3; extra == 'pdf'
Requires-Dist: markdown-pdf>=1.7; extra == 'pdf'
